act_dr6_lenslike/.DS_Store
act_dr6_lenslike/__init__.py
act_dr6_lenslike/act_dr6_lenslike.py
act_dr6_lenslike/tests/__init__.py
act_dr6_lenslike/tests/test_act.py
act_dr6_lenslike/tests/test_cobaya.py
act_dr6_lenslike-1.2.1.dist-info/licenses/LICENSE
act_dr6_lenslike-1.2.1.dist-info/WHEEL
act_dr6_lenslike-1.2.1.dist-info/METADATA
act_dr6_lenslike-1.2.1.dist-info/RECORD
