Metadata-Version: 2.4
Name: act_dr6_lenslike
Version: 1.2.1
Summary: Likelihood for the Atacama Cosmology Telescope DR6 CMB lensing data.
Author-email: Mathew Madhavacheril <mathm@sas.upenn.edu>, Ian Harrison <harrisoni@cardiff.ac.uk>
Classifier: License :: OSI Approved :: BSD License
License-File: LICENSE
Requires-Dist: numpy >=1
Requires-Dist: scipy >=1
Requires-Dist: pytest
Requires-Dist: tqdm
Requires-Dist: requests
Project-URL: Source, https://github.com/ACTCollaboration/act_dr6_lenslike
